{"duration": 3.3616597652435303, "input_args": {"imgs": "'D:/MRI/UCLA_CNP/preprocess/fmriprep/derivatives/sub-11077/func/sub-11077_task-rest_space-MNI152NLin2009cAsym_desc-preproc_bold.nii.gz'", "extraction_function": "<nilearn.maskers.nifti_labels_masker._ExtractionFunctor object at 0x0000027F7B67F8E0>", "parameters": "{'background_label': 0, 'detrend': True, 'dtype': None, 'high_pass': 0.01, 'high_variance_confounds': False, 'keep_masked_labels': True, 'labels': None, 'labels_img': <nibabel.nifti1.Nifti1Image object at 0x0000027F7B67CC70>, 'low_pass': 0.1, 'mask_img': <nibabel.nifti1.Nifti1Image object at 0x0000027F00759120>, 'reports': True, 'smoothing_fwhm': 4.0, 'standardize': 'zscore_sample', 'standardize_confounds': True, 'strategy': 'mean', 't_r': 2.0, 'target_shape': None, 'target_affine': None, 'clean_kwargs': {}}", "confounds": "[           csf  global_signal     rot_x     rot_y     rot_z   trans_x   trans_y   trans_z  white_matter\n0    10.464261       4.093178 -0.001450 -0.000394  0.000528 -0.059942 -0.053721 -0.158500      0.517504\n1     7.113051       1.007318 -0.001377 -0.000470  0.000492 -0.059932  0.019075 -0.092581      0.633385\n2     3.251105      -1.142856 -0.001951 -0.000470  0.000554 -0.059937 -0.022313 -0.092546      1.305834\n3    -2.355311      -1.329191 -0.001664 -0.000470  0.000272 -0.059940  0.043429 -0.110765     -0.616138\n4    -0.852619      -0.885195 -0.001932 -0.000470  0.000475 -0.059939 -0.038791 -0.110705     -1.442993\n..         ...            ...       ...       ...       ...       ...       ...       ...           ...\n147  -3.407462       1.114658  0.000523  0.000398  0.000091  0.076162  0.018650  0.227474     -0.775484\n148  -1.950958       0.866193  0.001229  0.000768 -0.000150  0.068873 -0.016636  0.210784     -2.034017\n149   0.124665      -0.992757  0.001229  0.000768 -0.000292  0.068880  0.027864  0.225509     -1.026571\n150  -2.570910      -1.386497  0.000613  0.000768 -0.000292  0.068880 -0.006151  0.240470     -1.665667\n151  -4.080772      -1.363846  0.000529  0.000624 -0.000422  0.076195  0.008153  0.251729     -2.017507\n\n[152 rows x 9 columns]]", "sample_mask": "None", "copy": "True", "dtype": "None"}}